README
setup.py
guoya_api.egg-info/PKG-INFO
guoya_api.egg-info/SOURCES.txt
guoya_api.egg-info/dependency_links.txt
guoya_api.egg-info/requires.txt
guoya_api.egg-info/top_level.txt
wuling/tool/__init__.py
wuling/tool/api_prj_init.py
wuling/tool/api_test_tool.py
wuling/tool/http_parser.py
wuling/tool/api_test_tool.py