Metadata-Version: 1.0
Name: guoya-api
Version: 0.1.4
Summary: 果芽API依赖包
Home-page: https://gitee.com/guoyasoft/guoya-api.git
Author: wuling
Author-email: wuling@guoyasoft.com
License: MIT Licence
Keywords: init,auto-api-test
Platform: python
